libqualia-neuralnetwork/CMakeLists.txt
libqualia-neuralnetwork/Metrics/Accuracy.h
libqualia-neuralnetwork/Metrics/MeanAbsoluteError.h
libqualia-neuralnetwork/Metrics/MeanSquaredError.h
libqualia-neuralnetwork/Metrics/Metric.h
libqualia-neuralnetwork/Metrics/PearsonCorrelationCoefficient.h
libqualia-neuralnetwork/Metrics/Slope.h
libqualia-neuralnetwork/NeuralNetwork.cpp
libqualia-neuralnetwork/NeuralNetwork.h
libqualia-neuralnetwork/__init__.py
qualia_codegen_core-2.5.0.dist-info/METADATA
qualia_codegen_core-2.5.0.dist-info/WHEEL
qualia_codegen_core-2.5.0.dist-info/entry_points.txt
qualia_codegen_core-2.5.0.dist-info/licenses/LICENSE
qualia_codegen_core/Allocator.py
qualia_codegen_core/Converter.py
qualia_codegen_core/DataConverter.py
qualia_codegen_core/MetricsConverter.py
qualia_codegen_core/Quantizer.py
qualia_codegen_core/Validator.py
qualia_codegen_core/__init__.py
qualia_codegen_core/assets/.editorconfig
qualia_codegen_core/assets/__init__.py
qualia_codegen_core/assets/include/defines.hh
qualia_codegen_core/assets/include/layers/activation.hh
qualia_codegen_core/assets/include/layers/add.hh
qualia_codegen_core/assets/include/layers/averagepool1d.hh
qualia_codegen_core/assets/include/layers/averagepool2d.hh
qualia_codegen_core/assets/include/layers/batchnorm1d.hh
qualia_codegen_core/assets/include/layers/batchnorm2d.hh
qualia_codegen_core/assets/include/layers/concatenate.hh
qualia_codegen_core/assets/include/layers/conv1d.hh
qualia_codegen_core/assets/include/layers/conv2d.hh
qualia_codegen_core/assets/include/layers/fc.hh
qualia_codegen_core/assets/include/layers/flatten.hh
qualia_codegen_core/assets/include/layers/maxpool1d.hh
qualia_codegen_core/assets/include/layers/maxpool2d.hh
qualia_codegen_core/assets/include/layers/permute.hh
qualia_codegen_core/assets/include/layers/samplenorm.hh
qualia_codegen_core/assets/include/layers/slice.hh
qualia_codegen_core/assets/include/layers/sum.hh
qualia_codegen_core/assets/include/metrics.hh
qualia_codegen_core/assets/include/model.hh
qualia_codegen_core/assets/include/number.hh
qualia_codegen_core/assets/layers/activation.cc
qualia_codegen_core/assets/layers/add.cc
qualia_codegen_core-2.5.0.dist-info/RECORD
