Metadata-Version: 2.1
Name: qualia-codegen-core
Version: 2.5.0
Summary: Generate portable C inference code from Keras or PyTorch model
Author-Email: Pierre-Emmanuel Novac <penovac@unice.fr>
License: AGPL-3.0-or-later
Classifier: Programming Language :: Python :: 3
Classifier: License :: OSI Approved :: GNU Affero General Public License v3
Classifier: Operating System :: OS Independent
Project-URL: homepage, https://github.com/LEAT-EDGE/qualia-codegen-core
Project-URL: documentation, https://leat-edge.github.io/qualia-codegen-core
Requires-Python: <3.14,>=3.9
Requires-Dist: numpy>=1.22.0
Requires-Dist: jinja2
Requires-Dist: typing_extensions; python_version < "3.12"
Provides-Extra: tensorflow
Requires-Dist: tensorflow>=2.6.0; extra == "tensorflow"
Requires-Dist: keras>=2.6.0; extra == "tensorflow"
Provides-Extra: pytorch
Requires-Dist: torch>=1.8.0; extra == "pytorch"
Requires-Dist: tabulate; extra == "pytorch"
Provides-Extra: graph
Requires-Dist: graphviz; extra == "graph"
Provides-Extra: tests
Requires-Dist: pytest; extra == "tests"
Requires-Dist: pytest-xdist; extra == "tests"
Provides-Extra: lint
Requires-Dist: ruff; extra == "lint"
Provides-Extra: typecheck
Requires-Dist: mypy; extra == "typecheck"
Requires-Dist: pyright; extra == "typecheck"
Provides-Extra: docs
Requires-Dist: pdm; extra == "docs"
Requires-Dist: sphinx; extra == "docs"
Requires-Dist: sphinx-rtd-theme; extra == "docs"
Requires-Dist: myst-parser; extra == "docs"
